phasefinder/__init__.py
phasefinder/dataset.py
phasefinder/grid_search_results_20240731_175605.csv
phasefinder/grid_search_results_20240801_132617.csv
phasefinder/infer.py
phasefinder/postproc_gridsearch.py
phasefinder/predictor.py
phasefinder/test_model.py
phasefinder/test_postproc.py
phasefinder/train.py
phasefinder/val.py
phasefinder/audio/__init__.py
phasefinder/audio/log_filter.py
phasefinder/model/__init__.py
phasefinder/model/attention.py
phasefinder/model/decoder.py
phasefinder/model/feature1d.py
phasefinder/model/model_attn.py
phasefinder/model/model_noattn.py
phasefinder/model/pos_encoding.py
phasefinder/postproc/__init__.py
phasefinder/postproc/cleaner.py
phasefinder/postproc/hmm.py
phasefinder/utils/__init__.py
phasefinder/utils/detect_corruption.py
phasefinder/utils/get_device.py
phasefinder/utils/get_weights.py
phasefinder/utils/one_hots.py
phasefinder-0.0.3.dist-info/METADATA
phasefinder-0.0.3.dist-info/WHEEL
phasefinder-0.0.3.dist-info/entry_points.txt
phasefinder-0.0.3.dist-info/license_files/LICENSE
phasefinder-0.0.3.dist-info/RECORD
