Metadata-Version: 2.1
Name: phasefinder
Version: 0.0.3
Summary: rotational beat estimation model
Project-URL: Homepage, https://github.com/bleugreen/phasefinder
Project-URL: Issues, https://github.com/bleugreen/phasefinder/issues
Author-email: bleugreen <bleugreendesign@gmail.com>
Classifier: License :: OSI Approved :: GNU Affero General Public License v3
Classifier: Operating System :: OS Independent
Classifier: Programming Language :: Python :: 3
Requires-Python: >=3.8
Requires-Dist: deeprhythm
Requires-Dist: h5py
Requires-Dist: librosa
Requires-Dist: librosa
Requires-Dist: mir_eval
Requires-Dist: nnAudio
Requires-Dist: numpy<2.0.0
Requires-Dist: pytorch-tcn
Requires-Dist: soundfile
Requires-Dist: torch
Requires-Dist: torchaudio
Requires-Dist: tqdm
